pyecobee/__init__.py
pyecobee/const.py
pyecobee/errors.py
pyecobee/util.py
python_ecobee_api-0.3.1.dist-info/licenses/LICENSE.txt
python_ecobee_api-0.3.1.dist-info/METADATA
python_ecobee_api-0.3.1.dist-info/WHEEL
python_ecobee_api-0.3.1.dist-info/top_level.txt
python_ecobee_api-0.3.1.dist-info/zip-safe
python_ecobee_api-0.3.1.dist-info/RECORD
