Metadata-Version: 2.4
Name: python-ecobee-api
Version: 0.3.1
Summary: Python API for talking to Ecobee thermostats
Home-page: https://github.com/nkgilley/python-ecobee-api
Author: Nolan Gilley
Author-email: nkgilley@gmail.com
License: MIT
License-File: LICENSE.txt
Requires-Dist: requests>=2.25
Dynamic: author
Dynamic: author-email
Dynamic: home-page
Dynamic: license
Dynamic: license-file
Dynamic: requires-dist
Dynamic: summary
